shibuya/__init__.py
shibuya/_patch.py
shibuya/_pygments.py
shibuya/_wrapper.py
shibuya/sponsors.py
shibuya/locale/de/LC_MESSAGES/sphinx.mo
shibuya/locale/es/LC_MESSAGES/sphinx.mo
shibuya/locale/fr/LC_MESSAGES/sphinx.mo
shibuya/locale/ja/LC_MESSAGES/sphinx.mo
shibuya/locale/ko/LC_MESSAGES/sphinx.mo
shibuya/locale/pt/LC_MESSAGES/sphinx.mo
shibuya/locale/pt_BR/LC_MESSAGES/sphinx.mo
shibuya/locale/zh/LC_MESSAGES/sphinx.mo
shibuya/locale/zh_TW/LC_MESSAGES/sphinx.mo
shibuya/theme/shibuya/base.html
shibuya/theme/shibuya/layout.html
shibuya/theme/shibuya/localtoc.html
shibuya/theme/shibuya/page.html
shibuya/theme/shibuya/relations.html
shibuya/theme/shibuya/search.html
shibuya/theme/shibuya/searchbox.html
shibuya/theme/shibuya/theme.conf
shibuya/theme/shibuya/components/alternate-links.html
shibuya/theme/shibuya/components/back-to-top.html
shibuya/theme/shibuya/components/breadcrumbs.html
shibuya/theme/shibuya/components/copy-page-button.html
shibuya/theme/shibuya/components/discussion-link.html
shibuya/theme/shibuya/components/foot-copyright.html
shibuya/theme/shibuya/components/foot-socials.html
shibuya/theme/shibuya/components/meta-opengraph.html
shibuya/theme/shibuya/components/nav-languages.html
shibuya/theme/shibuya/components/nav-links.html
shibuya/theme/shibuya/components/nav-socials.html
shibuya/theme/shibuya/components/nav-versions.html
shibuya/theme/shibuya/components/navigation.html
shibuya/theme/shibuya/components/searchbox.html
shibuya/theme/shibuya/components/theme-switch.html
shibuya/theme/shibuya/extensions/buysellads.html
shibuya/theme/shibuya/layout/404.html
shibuya/theme/shibuya/layout/compact.html
shibuya/theme/shibuya/layout/default.html
shibuya/theme/shibuya/layout/landing.html
shibuya/theme/shibuya/layout/simple.html
shibuya/theme/shibuya/partials/banner.html
shibuya/theme/shibuya/partials/extra-foot.html
shibuya/theme/shibuya/partials/extra-head.html
shibuya/theme/shibuya/partials/foot-socials.html
shibuya-2026.1.9.dist-info/licenses/LICENSE
shibuya-2026.1.9.dist-info/METADATA
shibuya-2026.1.9.dist-info/WHEEL
shibuya-2026.1.9.dist-info/entry_points.txt
shibuya-2026.1.9.dist-info/top_level.txt
shibuya-2026.1.9.dist-info/RECORD
