Metadata-Version: 2.4
Name: shibuya
Version: 2026.1.9
Summary: A clean, responsive, and customizable Sphinx documentation theme with light/dark mode.
Author-email: Hsiaoming Yang <me@lepture.com>
License: BSD-3-Clause
Project-URL: Source, https://github.com/lepture/shibuya
Project-URL: Documentation, https://shibuya.lepture.com/
Project-URL: Sponsors, https://github.com/sponsors/lepture
Classifier: Framework :: Sphinx
Classifier: Framework :: Sphinx :: Theme
Classifier: Development Status :: 5 - Production/Stable
Classifier: License :: OSI Approved :: BSD License
Classifier: Environment :: Web Environment
Classifier: Intended Audience :: Developers
Classifier: Programming Language :: Python :: 3
Classifier: Programming Language :: Python :: 3.10
Classifier: Programming Language :: Python :: 3.11
Classifier: Programming Language :: Python :: 3.12
Classifier: Programming Language :: Python :: 3.13
Classifier: Programming Language :: Python :: 3.14
Classifier: Operating System :: OS Independent
Classifier: Topic :: Documentation
Classifier: Topic :: Software Development :: Documentation
Requires-Python: >=3.10
License-File: LICENSE
Requires-Dist: Sphinx
Requires-Dist: pygments-styles
Dynamic: license-file
